[{
        "id": "COLABIS_REST_TEST",
        "label": "COLABIS-Data via WMS",
        "description": "Returns COLABIS-Data via a WM-Service",
        "href": "https://geoserver.colabis.de/geoserver/wms",
        "baseURLService" : "https://geoserver.colabis.de/geoserver/",
        "layers": [{
            "id": "layer1",
            "href": "<baseURL>/services/services1/maps/layer1"
        }, {
            "id": "layer2",
            "href": "<baseURL>/services/services1/maps/layer2"
        }],
        "capabilities": [{
            "maps": "http://localhost:8001/service/wms/maps",
            "features": "http://localhost:8001/service/wms/features"
        }]
    }

]
